text_manipulations/__init__.py
text_manipulations-0.1.0.dist-info/WHEEL
text_manipulations-0.1.0.dist-info/METADATA
text_manipulations-0.1.0.dist-info/license_files/LICENSE
text_manipulations-0.1.0.dist-info/RECORD
